{
  "id": "/providers/Microsoft.Authorization/policyDefinitions/20a29c64-5c24-4d18-aedb-c476d329df20",
  "name": "20a29c64-5c24-4d18-aedb-c476d329df20",
  "properties": {
    "description": "Description Custom Manual - MCSB Baseline item IM-3 for ExpressRoute",
    "displayName": "MCSB Baseline item IM-3 for ExpressRoute",
    "metadata": {
      "offeringName": "ExpressRoute",
      "offeringId": "3e80411f-1930-4048-abf3-235c22b3850a",
      "mcsb": {
        "mcsbId": "IM-3",
        "features": [
          {
            "featureId": "MANAGED_IDENTITIES",
            "featureName": "Managed Identities",
            "featureDescription": "Data plane actions support authentication using managed identities.",
            "featureSupport": "False",
            "featureGuidance": "This feature is not supported to secure this service.",
            "featureReference": "Not Applicable",
            "enabledByDefault": "Not Applicable",
            "customerActionsDescription": "Manage application identities securely and automatically"
          },
          {
            "featureId": "SERVICE_PRINCIPAL",
            "featureName": "Service Principals",
            "featureDescription": "Data plane supports authentication using service principals.",
            "featureSupport": "False",
            "featureGuidance": "This feature is not supported to secure this service.",
            "featureReference": "Not Applicable",
            "enabledByDefault": "Not Applicable",
            "customerActionsDescription": "Manage application identities securely and automatically"
          }
        ],
        "automatedPolicyAvailability": [],
        "frameworkControls": [
          "NIST_SP_800-53_R4_AC-3",
          "NIST_SP_800-53_R4_AC-2",
          "NIST_SP_800-53_R4_IA-5",
          "NIST_SP_800-53_R4_IA-9",
          "NIST_SP_800-53_R4_IA-4",
          "PCI_DSS_v4.0_8.6.2",
          "PCI_DSS_v4.0_8.6.3",
          "PCI_DSS_v4.0_8.6.1"
        ]
      },
      "version": "1.0.0",
      "category": "Regulatory Compliance"
    },
    "mode": "All",
    "policyType": "Custom",
    "policyRule": {
      "if": {
        "allOf": [
          {
            "field": "type",
            "in": [
              "Microsoft.Resources/subscriptions",
              "Microsoft.Resources/subscriptions/resourceGroups"
            ]
          },
          {
            "value": "false",
            "equals": "true"
          }
        ]
      },
      "then": {
        "effect": "Manual",
        "details": {
          "defaultState": "Unknown"
        }
      }
    }
  }
}