{
  "id": "/providers/Microsoft.Authorization/policyDefinitions/057b8c5c-8103-437b-9f34-f15d5fbe7cb6",
  "name": "057b8c5c-8103-437b-9f34-f15d5fbe7cb6",
  "properties": {
    "description": "Microsoft implements this Security Assessment and Authorization control",
    "displayName": "Custom - Microsoft Managed Control 1011 - Security Authorization",
    "metadata": {
      "version": "1.0.0",
      "category": "Regulatory Compliance",
      "additionalMetadataId": "/providers/Microsoft.PolicyInsights/policyMetadata/ACF1011",
      "standardControlMappings": [
        "NIST_SP_800-53_R4_AC-2",
        "PCI_DSS_v4.0_7.2.4"
      ]
    },
    "mode": "Indexed",
    "policyType": "Custom",
    "policyRule": {
      "if": {
        "allOf": [
          {
            "field": "type",
            "in": [
              "Microsoft.Resources/subscriptions",
              "Microsoft.Resources/subscriptions/resourceGroups"
            ]
          },
          {
            "value": "false",
            "equals": "true"
          }
        ]
      },
      "then": {
        "effect": "audit"
      }
    }
  }
}