{
  "id": "/providers/Microsoft.Authorization/policyDefinitions/4448a7ac-1577-4af5-afbb-cb9d7d26c221",
  "name": "4448a7ac-1577-4af5-afbb-cb9d7d26c221",
  "properties": {
    "description": "Microsoft implements this Security Assessment and Authorization control",
    "displayName": "Custom - Microsoft Managed Control 1860 - Security Authorization",
    "metadata": {
      "version": "1.0.0",
      "category": "Regulatory Compliance",
      "additionalMetadataId": "/providers/Microsoft.PolicyInsights/policyMetadata/ACF1860",
      "standardControlMappings": [
        "NIST_SP_800-53_R4_TR-1"
      ]
    },
    "mode": "Indexed",
    "policyType": "Custom",
    "policyRule": {
      "if": {
        "allOf": [
          {
            "field": "type",
            "in": [
              "Microsoft.Resources/subscriptions",
              "Microsoft.Resources/subscriptions/resourceGroups"
            ]
          },
          {
            "value": "false",
            "equals": "true"
          }
        ]
      },
      "then": {
        "effect": "audit"
      }
    }
  }
}