{
  "id": "/providers/Microsoft.Authorization/policyDefinitions/7dd305f6-eeb6-419a-8966-d577c3419bd4",
  "name": "7dd305f6-eeb6-419a-8966-d577c3419bd4",
  "properties": {
    "description": "Microsoft implements this Security Assessment and Authorization control",
    "displayName": "Custom - Microsoft Managed Control 1530 - Security Authorization",
    "metadata": {
      "version": "1.0.0",
      "category": "Regulatory Compliance",
      "additionalMetadataId": "/providers/Microsoft.PolicyInsights/policyMetadata/ACF1530",
      "standardControlMappings": [
        "NIST_SP_800-53_R4_PS-7"
      ]
    },
    "mode": "Indexed",
    "policyType": "Custom",
    "policyRule": {
      "if": {
        "allOf": [
          {
            "field": "type",
            "in": [
              "Microsoft.Resources/subscriptions",
              "Microsoft.Resources/subscriptions/resourceGroups"
            ]
          },
          {
            "value": "false",
            "equals": "true"
          }
        ]
      },
      "then": {
        "effect": "audit"
      }
    }
  }
}