{
  "id": "/providers/Microsoft.Authorization/policyDefinitions/e231c806-b74e-43f2-a442-e3f3b271baa1",
  "name": "e231c806-b74e-43f2-a442-e3f3b271baa1",
  "properties": {
    "description": "Microsoft implements this Security Assessment and Authorization control",
    "displayName": "Custom - Microsoft Managed Control 1708 - Security Authorization",
    "metadata": {
      "version": "1.0.0",
      "category": "Regulatory Compliance",
      "additionalMetadataId": "/providers/Microsoft.PolicyInsights/policyMetadata/ACF1708",
      "standardControlMappings": [
        "NIST_SP_800-53_R4_SI-6",
        "PCI_DSS_v4.0_10.7.1",
        "PCI_DSS_v4.0_10.7.2",
        "PCI_DSS_v4.0_10.7.3"
      ]
    },
    "mode": "Indexed",
    "policyType": "Custom",
    "policyRule": {
      "if": {
        "allOf": [
          {
            "field": "type",
            "in": [
              "Microsoft.Resources/subscriptions",
              "Microsoft.Resources/subscriptions/resourceGroups"
            ]
          },
          {
            "value": "false",
            "equals": "true"
          }
        ]
      },
      "then": {
        "effect": "audit"
      }
    }
  }
}