{
  "id": "/providers/Microsoft.Authorization/policyDefinitions/e7a7f82a-d244-4a7a-a49d-bd919733373a",
  "name": "e7a7f82a-d244-4a7a-a49d-bd919733373a",
  "properties": {
    "description": "Microsoft implements this Security Assessment and Authorization control",
    "displayName": "Custom - Microsoft Managed Control 1402 - Security Authorization",
    "metadata": {
      "version": "1.0.0",
      "category": "Regulatory Compliance",
      "additionalMetadataId": "/providers/Microsoft.PolicyInsights/policyMetadata/ACF1402",
      "standardControlMappings": [
        "NIST_SP_800-53_R4_MA-2(2)"
      ]
    },
    "mode": "Indexed",
    "policyType": "Custom",
    "policyRule": {
      "if": {
        "allOf": [
          {
            "field": "type",
            "in": [
              "Microsoft.Resources/subscriptions",
              "Microsoft.Resources/subscriptions/resourceGroups"
            ]
          },
          {
            "value": "false",
            "equals": "true"
          }
        ]
      },
      "then": {
        "effect": "audit"
      }
    }
  }
}