{
  "id": "/providers/Microsoft.Authorization/policyDefinitions/90f49e00-1a7b-43cf-8995-820830c14c2c",
  "name": "90f49e00-1a7b-43cf-8995-820830c14c2c",
  "properties": {
    "description": "Description Custom Manual - MCSB Baseline item AM-2 for Azure Migrate",
    "displayName": "MCSB Baseline item AM-2 for Azure Migrate",
    "metadata": {
      "offeringName": "Azure Migrate",
      "offeringId": "9d8a7fdc-4f15-4682-b589-78a85286c82c",
      "mcsb": {
        "mcsbId": "AM-2",
        "features": [
          {
            "featureId": "AZURE_POLICY_SUPPORTED",
            "featureName": "Azure Policy Support",
            "featureDescription": "Service configurations can be monitored and enforced via Azure Policy.",
            "featureSupport": "True",
            "featureGuidance": "Use Microsoft Defender for Cloud to configure Azure Policy to audit and enforce configurations of your Azure resources. Use Azure Monitor to create alerts when there is a configuration deviation detected on the resources. Use Azure Policy [deny] and [deploy if not exists] effects to enforce secure configuration across Azure resources.",
            "featureReference": "https://learn.microsoft.com/azure/migrate/policy-reference",
            "enabledByDefault": "False",
            "customerActionsDescription": "Use only approved services\n"
          }
        ],
        "automatedPolicyAvailability": [],
        "frameworkControls": [
          "CIS_Azure_2.0.0_7.5",
          "CIS_Azure_2.0.0_5.5",
          "NIST_SP_800-53_R4_CM-8",
          "NIST_SP_800-53_R4_PM-5",
          "PCI_DSS_v4.0_2.2.6",
          "PCI_DSS_v4.0_2.2.5",
          "PCI_DSS_v4.0_2.2.4"
        ]
      },
      "version": "1.0.0",
      "category": "Regulatory Compliance"
    },
    "mode": "All",
    "policyType": "Custom",
    "policyRule": {
      "if": {
        "allOf": [
          {
            "field": "type",
            "in": [
              "Microsoft.Resources/subscriptions",
              "Microsoft.Resources/subscriptions/resourceGroups"
            ]
          },
          {
            "value": "false",
            "equals": "true"
          }
        ]
      },
      "then": {
        "effect": "Manual",
        "details": {
          "defaultState": "Unknown"
        }
      }
    }
  }
}