{
  "id": "/providers/Microsoft.Authorization/policyDefinitions/0e3245ff-ef64-45f5-8a8f-0c5f594a2faf",
  "name": "0e3245ff-ef64-45f5-8a8f-0c5f594a2faf",
  "properties": {
    "description": "Description Custom Manual - MCSB Baseline item PA-8 for Azure Stack HCI",
    "displayName": "MCSB Baseline item PA-8 for Azure Stack HCI",
    "metadata": {
      "offeringName": "Azure Stack HCI",
      "offeringId": "40712a7c-75ad-4d57-b314-d77c9ec45c05",
      "mcsb": {
        "mcsbId": "PA-8",
        "features": [
          {
            "featureId": "CUSTOMER_LOCKBOX_SUPPORTED",
            "featureName": "Customer Lockbox",
            "featureDescription": "Customer Lockbox can be used for Microsoft support access.",
            "featureSupport": "False",
            "featureGuidance": "This feature is not supported to secure this service.",
            "featureReference": "Not Applicable",
            "enabledByDefault": "Not Applicable",
            "customerActionsDescription": "Determine access process for cloud provider support\n\n"
          }
        ],
        "automatedPolicyAvailability": [],
        "frameworkControls": [
          "CIS_Azure_2.0.0_1.20",
          "NIST_SP_800-53_R4_AC-2",
          "NIST_SP_800-53_R4_AC-4",
          "NIST_SP_800-53_R4_AC-3"
        ]
      },
      "version": "1.0.0",
      "category": "Regulatory Compliance"
    },
    "mode": "All",
    "policyType": "Custom",
    "policyRule": {
      "if": {
        "allOf": [
          {
            "field": "type",
            "in": [
              "Microsoft.Resources/subscriptions",
              "Microsoft.Resources/subscriptions/resourceGroups"
            ]
          },
          {
            "value": "false",
            "equals": "true"
          }
        ]
      },
      "then": {
        "effect": "Manual",
        "details": {
          "defaultState": "Unknown"
        }
      }
    }
  }
}